mpmathbyyhu/__init__.py
mpmathbyyhu/basic_operations.py
mpmathbyyhu/geometry.py
mpmathbyyhu/random_generators.py
mpmathbyyhu/statistics.py
mpmathbyyhu-0.1.1.dist-info/licenses/LICENSE
mpmathbyyhu-0.1.1.dist-info/METADATA
mpmathbyyhu-0.1.1.dist-info/WHEEL
mpmathbyyhu-0.1.1.dist-info/top_level.txt
mpmathbyyhu-0.1.1.dist-info/RECORD
