Metadata-Version: 2.4
Name: mpmathbyyhu
Version: 0.1.1
Summary: A comprehensive mathematics utility library
Author-email: yhu <246441142@qq.com>
Project-URL: Homepage, https://github.com/yhu2025
Project-URL: Repository, https://github.com/yhu2025
Classifier: Programming Language :: Python :: 3
Classifier: License :: OSI Approved :: MIT License
Classifier: Operating System :: OS Independent
Requires-Python: >=3.6.6
License-File: LICENSE
Dynamic: license-file
